tests/__init__.py
tests/test_demo_methods.py
welovenad/__init__.py
welovenad/demo.py
welovenad/other_methods.py
welovenad-1.0.0.dist-info/METADATA
welovenad-1.0.0.dist-info/WHEEL
welovenad-1.0.0.dist-info/top_level.txt
welovenad-1.0.0.dist-info/RECORD
