Metadata-Version: 2.1
Name: welovenad
Version: 1.0.0
Summary: a demo package for NAD !
Home-page: https://link/of/your/package
Author: Robin Champseix
Author-email: robin.champseix@gmail.com
License: MIT
Platform: UNKNOWN
Classifier: Programming Language :: Python :: 3
Classifier: Operating System :: OS Independent
Requires-Python: >=3.6
Requires-Dist: numpy (>=1.15.1)
Requires-Dist: pandas (>=0.23.4)
